cars_mesh/__init__.py
cars_mesh/cli.py
cars_mesh/cli_evaluate.py
cars_mesh/config.py
cars_mesh/evaluate_pipeline.py
cars_mesh/logging.json
cars_mesh/param.py
cars_mesh/reconstruct_pipeline.py
cars_mesh/setup_logging.py
cars_mesh/state_machine.py
cars_mesh/core/__init__.py
cars_mesh/core/denoise_mesh.py
cars_mesh/core/denoise_pcd.py
cars_mesh/core/filter.py
cars_mesh/core/mesh.py
cars_mesh/core/simplify_mesh.py
cars_mesh/core/texture.py
cars_mesh/tools/__init__.py
cars_mesh/tools/handlers.py
cars_mesh/tools/mesh_io.py
cars_mesh/tools/metrics.py
cars_mesh/tools/point_cloud_io.py
cars_mesh/tools/rpc.py
tests/__init__.py
tests/helpers.py
tests/test_mesh3d.py
cars_mesh-0.1.2.dist-info/LICENSE
cars_mesh-0.1.2.dist-info/METADATA
cars_mesh-0.1.2.dist-info/WHEEL
cars_mesh-0.1.2.dist-info/entry_points.txt
cars_mesh-0.1.2.dist-info/top_level.txt
cars_mesh-0.1.2.dist-info/RECORD
