Metadata-Version: 2.1
Name: cars-mesh
Version: 0.1.2
Summary: "3D Surface reconstruction with texture and classification from remote sensing photogrammetric point cloud"
Home-page: https://github.com/CNES/cars-mesh
Author: CNES
Author-email: cars@cnes.fr
License: Apache Software License 2.0
Keywords: cars-mesh,3D,DEM,cars,pandora,photogrammetry
Platform: any
Classifier: Development Status :: 4 - Beta
Classifier: Intended Audience :: Developers
Classifier: Intended Audience :: End Users/Desktop
Classifier: Intended Audience :: Science/Research
Classifier: Environment :: Console
Classifier: Topic :: Software Development :: Libraries :: Python Modules
Classifier: License :: OSI Approved :: Apache Software License
Classifier: Operating System :: OS Independent
Classifier: Natural Language :: English
Classifier: Programming Language :: Python
Classifier: Programming Language :: Python :: 3
Classifier: Programming Language :: Python :: 3.8
Requires-Python: >=3.8
License-File: LICENSE
Requires-Dist: argparse
Requires-Dist: numpy
Requires-Dist: laspy[laszip]
Requires-Dist: open3d-cpu
Requires-Dist: pandas
Requires-Dist: scipy
Requires-Dist: plyfile
Requires-Dist: matplotlib
Requires-Dist: pyproj
Requires-Dist: transitions
Requires-Dist: rasterio
Provides-Extra: dev
Requires-Dist: pre-commit ; extra == 'dev'
Requires-Dist: isort >=5.8.0 ; extra == 'dev'
Requires-Dist: black >=21.5b0 ; extra == 'dev'
Requires-Dist: flake8 >=3.9.1 ; extra == 'dev'
Requires-Dist: flake8-comprehensions >=3.4.0 ; extra == 'dev'
Requires-Dist: flake8-bugbear >=21.4.3 ; extra == 'dev'
Requires-Dist: pylint ; extra == 'dev'
Requires-Dist: setuptools-scm ; extra == 'dev'
Requires-Dist: virtualenv ; extra == 'dev'
Requires-Dist: configupdater ; extra == 'dev'
Requires-Dist: twine ; extra == 'dev'
Requires-Dist: pytest ; extra == 'dev'
Requires-Dist: pytest-cov ; extra == 'dev'
Requires-Dist: tox ; extra == 'dev'
Provides-Extra: docs
Requires-Dist: sphinx ; extra == 'docs'
Requires-Dist: sphinx-rtd-theme ; extra == 'docs'
Requires-Dist: sphinx-autoapi ; extra == 'docs'
